odoo/addons/stock_available_to_promise_release_carrier_alternative/README.rst
odoo/addons/stock_available_to_promise_release_carrier_alternative/__init__.py
odoo/addons/stock_available_to_promise_release_carrier_alternative/__manifest__.py
odoo/addons/stock_available_to_promise_release_carrier_alternative/i18n/it.po
odoo/addons/stock_available_to_promise_release_carrier_alternative/i18n/stock_available_to_promise_release_carrier_alternative.pot
odoo/addons/stock_available_to_promise_release_carrier_alternative/models/__init__.py
odoo/addons/stock_available_to_promise_release_carrier_alternative/models/delivery_carrier.py
odoo/addons/stock_available_to_promise_release_carrier_alternative/models/procurement_group.py
odoo/addons/stock_available_to_promise_release_carrier_alternative/models/stock_move.py
odoo/addons/stock_available_to_promise_release_carrier_alternative/models/stock_picking.py
odoo/addons/stock_available_to_promise_release_carrier_alternative/readme/CONFIGURE.md
odoo/addons/stock_available_to_promise_release_carrier_alternative/readme/CONTRIBUTORS.md
odoo/addons/stock_available_to_promise_release_carrier_alternative/readme/DESCRIPTION.md
odoo/addons/stock_available_to_promise_release_carrier_alternative/static/description/icon.png
odoo/addons/stock_available_to_promise_release_carrier_alternative/static/description/index.html
odoo/addons/stock_available_to_promise_release_carrier_alternative/tests/__init__.py
odoo/addons/stock_available_to_promise_release_carrier_alternative/tests/common.py
odoo/addons/stock_available_to_promise_release_carrier_alternative/tests/test_delivery_carrier_alternative.py
odoo/addons/stock_available_to_promise_release_carrier_alternative/views/delivery_carrier.xml
odoo_addon_stock_available_to_promise_release_carrier_alternative-18.0.1.0.1.1.dist-info/METADATA
odoo_addon_stock_available_to_promise_release_carrier_alternative-18.0.1.0.1.1.dist-info/WHEEL
odoo_addon_stock_available_to_promise_release_carrier_alternative-18.0.1.0.1.1.dist-info/top_level.txt
odoo_addon_stock_available_to_promise_release_carrier_alternative-18.0.1.0.1.1.dist-info/RECORD
